multiplex_imaging_pipeline/__init__.py
multiplex_imaging_pipeline/multiplex_imaging_pipeline.py
multiplex_imaging_pipeline/ome.py
multiplex_imaging_pipeline/region_classification.py
multiplex_imaging_pipeline/region_features.py
multiplex_imaging_pipeline/segmentation.py
multiplex_imaging_pipeline/spatial_features.py
multiplex_imaging_pipeline/utils.py
multiplex_imaging_pipeline/compute1/__init__.py
multiplex_imaging_pipeline/compute1/generate_run_commands.py
multiplex_imaging_pipeline-0.2.1.dist-info/LICENSE
multiplex_imaging_pipeline-0.2.1.dist-info/METADATA
multiplex_imaging_pipeline-0.2.1.dist-info/WHEEL
multiplex_imaging_pipeline-0.2.1.dist-info/entry_points.txt
multiplex_imaging_pipeline-0.2.1.dist-info/top_level.txt
multiplex_imaging_pipeline-0.2.1.dist-info/RECORD
