Metadata-Version: 2.1
Name: multiplex-imaging-pipeline
Version: 0.2.1
Summary: A Python library for multiplex imaging analysis
Home-page: https://github.com/estorrs/multiplex-imaging-analysis
Author: Erik Storrs
Author-email: estorrs@wustl.edu
Keywords: multiplex imaging codex neighborhood analysis image segmentation visualization mibi codex phenocycler mihc hyperion
Classifier: License :: OSI Approved :: MIT License
Classifier: Programming Language :: Python :: 3.8
Classifier: Programming Language :: Python :: 3.9
Classifier: Programming Language :: Python :: 3.10
Requires-Python: >=3.8
License-File: LICENSE
Requires-Dist: pyyaml
Requires-Dist: numpy
Requires-Dist: pandas
Requires-Dist: einops
Requires-Dist: matplotlib
Requires-Dist: scanpy
Requires-Dist: seaborn
Requires-Dist: tifffile
Requires-Dist: ome-types
Requires-Dist: pydantic <=1.10.12
Requires-Dist: scikit-image
Requires-Dist: scikit-learn
Requires-Dist: imagecodecs >=2022.7.27
Requires-Dist: timm
Requires-Dist: torch
Requires-Dist: torchvision
Requires-Dist: pytorch-lightning
Provides-Extra: segmentation
Requires-Dist: deepcell ; extra == 'segmentation'
